coquille/__init__.py
coquille/prelude.py
coquille/prelude.pyi
coquille/py.typed
coquille/sequences.py
coquille/sequences.pyi
coquille/typeshed.pyi
Coquille-1.3.0.dist-info/LICENSE
Coquille-1.3.0.dist-info/METADATA
Coquille-1.3.0.dist-info/WHEEL
Coquille-1.3.0.dist-info/top_level.txt
Coquille-1.3.0.dist-info/RECORD
