Metadata-Version: 2.1
Name: Coquille
Version: 1.3.0
Summary: Coquille is a library that wraps terminal escape sequences as convenient functions.
Author: Qexat
License: MIT License
Project-URL: homepage, https://github.com/qexat/Coquille
Project-URL: repository, https://github.com/qexat/Coquille
Keywords: terminal,escape sequences
Classifier: License :: OSI Approved :: MIT License
Classifier: Programming Language :: Python :: 3
Requires-Python: >=3.9
License-File: LICENSE
Provides-Extra: dev
Requires-Dist: pytest ; extra == 'dev'
Requires-Dist: coverage ; extra == 'dev'
Requires-Dist: build ; extra == 'dev'
Requires-Dist: twine ; extra == 'dev'
